ezzybot
