Metadata-Version: 1.0
Name: ezzybot
Version: 2.1.0
Summary: Python IRC framework
Home-page: https://github.com/Azure-Developments/ezzybot
Author: EzzyBot team
Author-email: me@lukej.me
License: GNU
Platform: UNKNOWN
